atlassian_client/confluence/__init__.py
atlassian_client/confluence/client.py
atlassian_client/confluence/comments.py
atlassian_client/confluence/config.py
atlassian_client/confluence/pages.py
atlassian_client/confluence/search.py
atlassian_client/confluence/spaces.py
atlassian_client/jira/__init__.py
atlassian_client/jira/client.py
atlassian_client/jira/comments.py
atlassian_client/jira/config.py
atlassian_client/jira/epics.py
atlassian_client/jira/fields.py
atlassian_client/jira/formatting.py
atlassian_client/jira/issues.py
atlassian_client/jira/projects.py
atlassian_client/jira/search.py
atlassian_client/jira/transitions.py
atlassian_client/jira/users.py
atlassian_client/jira/utils.py
atlassian_client/jira/worklog.py
atlassian_client/models/__init__.py
atlassian_client/models/base.py
atlassian_client/models/confluence.py
atlassian_client/models/constants.py
atlassian_client/models/jira.py
atlassian_client/preprocessing/__init__.py
atlassian_client/preprocessing/base.py
atlassian_client/preprocessing/confluence.py
atlassian_client/preprocessing/jira.py
atlassian_client-0.1.6.dist-info/METADATA
atlassian_client-0.1.6.dist-info/WHEEL
atlassian_client-0.1.6.dist-info/licenses/LICENSE
atlassian_client-0.1.6.dist-info/RECORD
