Metadata-Version: 2.4
Name: atlassian-client
Version: 0.1.6
Summary: Async Python client for Atlassian products
Project-URL: Homepage, https://github.com/khanhct/atlassian
Project-URL: Documentation, https://github.com/khanhct/atlassian
Project-URL: Issues, https://github.com/khanhct/atlassian
Author-email: KhanhChu <trongkhanh.chu@gmail.com>
License: MIT
License-File: LICENSE
Keywords: api,async,atlassian,confluence,jira
Classifier: Development Status :: 3 - Alpha
Classifier: Framework :: AsyncIO
Classifier: Intended Audience :: Developers
Classifier: License :: OSI Approved :: MIT License
Classifier: Operating System :: OS Independent
Classifier: Programming Language :: Python :: 3
Classifier: Programming Language :: Python :: 3.8
Classifier: Programming Language :: Python :: 3.9
Classifier: Programming Language :: Python :: 3.10
Classifier: Programming Language :: Python :: 3.11
Classifier: Topic :: Software Development :: Libraries :: Python Modules
Requires-Python: >=3.10
Requires-Dist: atlassian-python-api>=3.41.16
Requires-Dist: beautifulsoup4>=4.12.3
Requires-Dist: httpx>=0.28.0
Requires-Dist: markdown-to-confluence>=0.3.0
Requires-Dist: markdown>=3.7.0
Requires-Dist: markdownify>=0.11.6
Requires-Dist: pydantic>=2.10.6
Requires-Dist: python-dotenv>=1.0.1
Requires-Dist: trio>=0.29.0
